modulo_teste-0.1.8.dist-info/WHEEL
modulo_teste-0.1.8.dist-info/DESCRIPTION.rst
modulo_teste-0.1.8.dist-info/top_level.txt
modulo_teste-0.1.8.dist-info/METADATA
modulo_teste-0.1.8.dist-info/RECORD
modulo_teste-0.1.8.dist-info/metadata.json
modulo_teste-0.1.8.data/data/python101/dados.json
programa/rodarprograma.py
programa/__main__.py
programa/__init__.py
programa/meuprograma.py
