Metadata-Version: 2.0
Name: modulo-teste
Version: 0.1.8
Summary: Exemplo para o Python 101
Home-page: http://www.aprendacodigo.com
Author: Aprenda Código
Author-email: contato@aprendacodigo.com
License: MIT
Keywords: exemplo tutorial desenvolvimento
Platform: UNKNOWN
Classifier: Development Status :: 4 - Beta
Classifier: Intended Audience :: Developers
Classifier: Topic :: Education :: Testing
Classifier: License :: OSI Approved :: MIT License
Classifier: Programming Language :: Python :: 3
Classifier: Programming Language :: Python :: 3.2
Classifier: Programming Language :: Python :: 3.3
Classifier: Programming Language :: Python :: 3.4
